MANIFEST.in
requirements.txt
setup.py
moz_inapp_pay/__init__.py
moz_inapp_pay/exc.py
moz_inapp_pay/processor.py
moz_inapp_pay/verify.py
moz_inapp_pay.egg-info/PKG-INFO
moz_inapp_pay.egg-info/SOURCES.txt
moz_inapp_pay.egg-info/dependency_links.txt
moz_inapp_pay.egg-info/requires.txt
moz_inapp_pay.egg-info/top_level.txt
moz_inapp_pay/djangoapp/__init__.py
moz_inapp_pay/djangoapp/models.py
moz_inapp_pay/djangoapp/signals.py
moz_inapp_pay/djangoapp/urls.py
moz_inapp_pay/djangoapp/views.py