Metadata-Version: 1.0
Name: moz-inapp-pay
Version: 1.0.2
Summary: Utility for working with Mozilla in-app payments.
Home-page: https://github.com/kumar303/moz_inapp_pay
Author: Kumar McMillan
Author-email: kumar.mcmillan@gmail.com
License: MPL 2.0 (Mozilla Public License)
Platform: UNKNOWN
